{
  "component-definition": {
    "uuid": "73fc4f28-a4de-4b3e-bc91-783ba6715114",
    "metadata": {
      "title": "Component definition for example",
      "last-modified": "2023-10-13T19:18:05.663224+00:00",
      "version": "1.0",
      "oscal-version": "1.0.4"
    },
    "components": [
      {
        "uuid": "dc4823d8-f8a7-4b95-a776-2589a69f2bb3",
        "type": "service",
        "title": "Example",
        "description": "Example Application",
        "props": [
          {
            "name": "Rule_Id",
            "ns": "https://ibm.github.io/compliance-trestle/schemas/oscal",
            "value": "Test-rule_001",
            "remarks": "rule_set_0"
          },
          {
            "name": "Rule_Description",
            "ns": "https://ibm.github.io/compliance-trestle/schemas/oscal",
            "value": "Ensure all of the services are running these tests always",
            "remarks": "rule_set_0"
          },
          {
            "name": "Parameter_Id",
            "ns": "https://ibm.github.io/compliance-trestle/schemas/oscal",
            "value": "prm_1",
            "remarks": "rule_set_0"
          },
          {
            "name": "Parameter_Description",
            "ns": "https://ibm.github.io/compliance-trestle/schemas/oscal",
            "value": "prm_1 description",
            "remarks": "rule_set_0"
          },
          {
            "name": "Parameter_Value_Alternatives",
            "ns": "https://ibm.github.io/compliance-trestle/schemas/oscal",
            "value": "{'default': '5%', '5pc': '5%', '10pc': '10%', '15pc': '15%', '20pc': '20%'}",
            "remarks": "rule_set_0"
          }
        ],
        "control-implementations": [
          {
            "uuid": "9aa3bc62-9c78-4c04-8bb3-8aa47d6231f3",
            "source": "profiles/fedramp_rev5_high/profile.json",
            "description": "FedRAMP REV5 High Baseline",
            "set-parameters": [
              {
                "param-id": "prm_1",
                "values": [
                  "5%"
                ]
              }
            ],
            "implemented-requirements": [
              {
                "uuid": "a33cc5fd-32fd-470e-801a-423890ff8442",
                "control-id": "ac-1",
                "description": "",
                "props": [
                  {
                    "name": "Rule_Id",
                    "ns": "https://ibm.github.io/compliance-trestle/schemas/oscal",
                    "value": "Test-rule_001"
                  },
                  {
                    "name": "implementation-status",
                    "value": "planned"
                  }
                ]
              }
            ]
          }
        ]
      }
    ]
  }
}